topsis/102017190.py
topsis/__init__.py
Topsis_Varchasva_102017190-1.0.0.dist-info/LICENSE.txt
Topsis_Varchasva_102017190-1.0.0.dist-info/METADATA
Topsis_Varchasva_102017190-1.0.0.dist-info/WHEEL
Topsis_Varchasva_102017190-1.0.0.dist-info/entry_points.txt
Topsis_Varchasva_102017190-1.0.0.dist-info/top_level.txt
Topsis_Varchasva_102017190-1.0.0.dist-info/RECORD
