Metadata-Version: 2.1
Name: Topsis-Varchasva-102017190
Version: 1.0.0
Summary: Topsis package for MCDM problems
Home-page: UNKNOWN
Author: Varchasva Narain Singh
Author-email: vsingh5_be20@thapar.edu
License: UNKNOWN
Platform: UNKNOWN
Classifier: Programming Language :: Python :: 3
Classifier: Programming Language :: Python :: 3.6
Classifier: Programming Language :: Python :: 3.7
Classifier: License :: OSI Approved :: MIT License
Classifier: Operating System :: OS Independent
Requires-Python: >=3.6
License-File: LICENSE.txt
